main_memory.v
`timescale 1ns/1ps

module main_memory #(
    parameter ADDR_WIDTH   = 32,
    parameter DATA_WIDTH   = 32,
    parameter MEM_WORDS    = 256,
    parameter LATENCY      = 3,
    parameter OFFSET_WIDTH = $clog2(DATA_WIDTH/8),
    parameter MEM_AWIDTH   = $clog2(MEM_WORDS)
)(
    input wire clk,
    input wire reset,

    input wire                   mem_req,
    input wire                   mem_write,
    input wire [ADDR_WIDTH-1:0]  mem_addr,
    input wire [DATA_WIDTH-1:0]  mem_wdata,

    output reg [DATA_WIDTH-1:0] mem_rdata,
    output reg                  mem_ready
);

    reg [DATA_WIDTH-1:0] memory [0:MEM_WORDS-1];

    reg busy;

    reg                  saved_write;
    reg [ADDR_WIDTH-1:0] saved_addr;
    reg [DATA_WIDTH-1:0] saved_wdata;

    integer counter;
    integer i;

    wire [MEM_AWIDTH-1:0] saved_word_addr;

    assign saved_word_addr =
        saved_addr[OFFSET_WIDTH + MEM_AWIDTH - 1:
                   OFFSET_WIDTH];


    initial begin

        for (i = 0; i < MEM_WORDS; i = i + 1)
            memory[i] = 32'h1000_0000 + i;

    end


    always @(posedge clk) begin

        if (reset) begin

            busy <= 1'b0;

            mem_ready <= 1'b0;
            mem_rdata <= {DATA_WIDTH{1'b0}};

            saved_write <= 1'b0;
            saved_addr  <= {ADDR_WIDTH{1'b0}};
            saved_wdata <= {DATA_WIDTH{1'b0}};

            counter <= 0;

        end
        else begin

            /*
             * mem_ready is a one-cycle pulse
             */

            mem_ready <= 1'b0;


            /*
             * Accept new request
             */

            if (!busy && mem_req) begin

                busy <= 1'b1;

                saved_write <= mem_write;
                saved_addr  <= mem_addr;
                saved_wdata <= mem_wdata;

                counter <= LATENCY;

            end


            /*
             * Process current request
             */

            else if (busy) begin

                if (counter > 1) begin

                    counter <= counter - 1;

                end
                else begin

                    busy <= 1'b0;

                    mem_ready <= 1'b1;

                    if (saved_write) begin

                        memory[saved_word_addr]
                            <= saved_wdata;

                        $display(
                            "[MEM WRITE] t=%0t addr=%h data=%h",
                            $time,
                            saved_addr,
                            saved_wdata
                        );

                    end
                    else begin

                        mem_rdata
                            <= memory[saved_word_addr];

                        $display(
                            "[MEM READ] t=%0t addr=%h data=%h",
                            $time,
                            saved_addr,
                            memory[saved_word_addr]
                        );

                    end

                end

            end

        end

    end

endmodule

cache_controller.v
`timescale 1ns/1ps

module cache_controller #(
    parameter ADDR_WIDTH   = 32,
    parameter DATA_WIDTH   = 32,
    parameter BLOCKS    = 16,
    parameter INDEX_WIDTH  = $clog2(BLOCKS),
    parameter OFFSET_WIDTH = $clog2(DATA_WIDTH/8),
    parameter TAG_WIDTH    = ADDR_WIDTH - INDEX_WIDTH - OFFSET_WIDTH
)(
    input wire clk,
    input wire reset,

    // CPU interface
    input  wire                  cpu_req,
    input  wire                  cpu_write,
    input  wire [ADDR_WIDTH-1:0] cpu_addr,
    input  wire [DATA_WIDTH-1:0] cpu_wdata,

    output reg  [DATA_WIDTH-1:0] cpu_rdata,
    output reg                   cpu_ready,

    // Cache interface
    output wire [INDEX_WIDTH-1:0] cache_index,

    input wire [TAG_WIDTH-1:0]   cache_tag,
    input wire [DATA_WIDTH-1:0]  cache_data,
    input wire                   cache_valid,
    input wire                   cache_dirty,

    output reg                    cache_write_en,
    output reg [TAG_WIDTH-1:0]    cache_tag_in,
    output reg [DATA_WIDTH-1:0]   cache_data_in,
    output reg                    cache_valid_in,
    output reg                    cache_dirty_in,

    // Main memory interface
    output reg                   mem_req,
    output reg                   mem_write,
    output reg [ADDR_WIDTH-1:0] mem_addr,
    output reg [DATA_WIDTH-1:0] mem_wdata,

    input wire [DATA_WIDTH-1:0] mem_rdata,
    input wire                  mem_ready
);

    localparam IDLE       = 3'd0;
    localparam LOOKUP     = 3'd1;
    localparam WRITE_BACK = 3'd2;
    localparam ALLOCATE   = 3'd3;
    localparam UPDATE     = 3'd4;

    reg [2:0] state;

    reg [ADDR_WIDTH-1:0] req_addr;
    reg [DATA_WIDTH-1:0] req_wdata;
    reg                  req_write;

    wire [TAG_WIDTH-1:0] req_tag;
    wire [INDEX_WIDTH-1:0] req_index;

    wire cache_hit;

    assign req_tag =
        req_addr[ADDR_WIDTH-1:
                 OFFSET_WIDTH + INDEX_WIDTH];

    assign req_index =
        req_addr[OFFSET_WIDTH + INDEX_WIDTH - 1:
                 OFFSET_WIDTH];

    assign cache_index = req_index;

    assign cache_hit =
        cache_valid &&
        (cache_tag == req_tag);


    /*
     * Sequential controller
     */

    always @(posedge clk) begin

        if (reset) begin

            state <= IDLE;

            req_addr  <= {ADDR_WIDTH{1'b0}};
            req_wdata <= {DATA_WIDTH{1'b0}};
            req_write <= 1'b0;

            cpu_rdata <= {DATA_WIDTH{1'b0}};
            cpu_ready <= 1'b0;

            cache_write_en <= 1'b0;
            cache_tag_in   <= {TAG_WIDTH{1'b0}};
            cache_data_in  <= {DATA_WIDTH{1'b0}};
            cache_valid_in <= 1'b0;
            cache_dirty_in <= 1'b0;

        end
        else begin

            /*
             * Default pulse outputs
             */

            cpu_ready      <= 1'b0;
            cache_write_en <= 1'b0;


            case (state)

                /*
                 * Wait for CPU request
                 */

                IDLE: begin

                    if (cpu_req) begin

                        req_addr  <= cpu_addr;
                        req_wdata <= cpu_wdata;
                        req_write <= cpu_write;

                        state <= LOOKUP;

                    end

                end


                /*
                 * Tag lookup
                 */

                LOOKUP: begin

                    if (cache_hit) begin

                        /*
                         * WRITE HIT
                         */

                        if (req_write) begin

                            cache_write_en <= 1'b1;

                            cache_tag_in   <= req_tag;
                            cache_data_in  <= req_wdata;
                            cache_valid_in <= 1'b1;
                            cache_dirty_in <= 1'b1;

                            cpu_ready <= 1'b1;

                        end

                        /*
                         * READ HIT
                         */

                        else begin

                            cpu_rdata <= cache_data;
                            cpu_ready <= 1'b1;

                        end

                        state <= IDLE;

                    end

                    /*
                     * CACHE MISS
                     */

                    else begin

                        if (cache_valid && cache_dirty)
                            state <= WRITE_BACK;
                        else
                            state <= ALLOCATE;

                    end

                end


                /*
                 * Write dirty victim to memory
                 */

                WRITE_BACK: begin

                    if (mem_ready) begin
                        state <= ALLOCATE;
                    end

                end


                /*
                 * Fetch requested word
                 */

                ALLOCATE: begin

                    if (mem_ready) begin

                        cache_write_en <= 1'b1;

                        cache_tag_in   <= req_tag;
                        cache_data_in  <= mem_rdata;
                        cache_valid_in <= 1'b1;
                        cache_dirty_in <= 1'b0;

                        /*
                         * READ MISS COMPLETE
                         */

                        if (!req_write) begin

                            cpu_rdata <= mem_rdata;
                            cpu_ready <= 1'b1;

                            state <= IDLE;

                        end

                        /*
                         * WRITE MISS
                         */

                        else begin

                            state <= UPDATE;

                        end

                    end

                end


                /*
                 * Write-allocate update
                 */

                UPDATE: begin

                    cache_write_en <= 1'b1;

                    cache_tag_in   <= req_tag;
                    cache_data_in  <= req_wdata;
                    cache_valid_in <= 1'b1;
                    cache_dirty_in <= 1'b1;

                    cpu_ready <= 1'b1;

                    state <= IDLE;

                end


                default: begin
                    state <= IDLE;
                end

            endcase

        end

    end


    /*
     * Memory request logic
     */

    /*
 * Main memory request generation
 *
 * mem_req is suppressed while mem_ready is asserted.
 * This prevents the memory from re-accepting a completed
 * request before the FSM changes state.
 */

always @(*) begin

    mem_req   = 1'b0;
    mem_write = 1'b0;
    mem_addr  = {ADDR_WIDTH{1'b0}};
    mem_wdata = {DATA_WIDTH{1'b0}};

    case (state)

        WRITE_BACK: begin

            /*
             * Stop asserting request once memory
             * acknowledges the transaction.
             */

            if (!mem_ready) begin

                mem_req   = 1'b1;
                mem_write = 1'b1;

                mem_addr = {
                    cache_tag,
                    req_index,
                    {OFFSET_WIDTH{1'b0}}
                };

                mem_wdata = cache_data;

            end

        end


        ALLOCATE: begin

            /*
             * Read requested word from memory.
             */

            if (!mem_ready) begin

                mem_req   = 1'b1;
                mem_write = 1'b0;

                mem_addr = {
                    req_tag,
                    req_index,
                    {OFFSET_WIDTH{1'b0}}
                };

            end

        end


        default: begin

            mem_req   = 1'b0;
            mem_write = 1'b0;
            mem_addr  = {ADDR_WIDTH{1'b0}};
            mem_wdata = {DATA_WIDTH{1'b0}};

        end

    endcase

end

endmodule

cache_memory.v
module cache_memory #(
    parameter ADDR_WIDTH = 32,                                          // 32-bit address lines
    parameter DATA_WIDTH = 32,                                          // 32-bit data lines
    parameter BLOCKS = 16,                                              // Total number of blocks in cache memory
    parameter INDEX_WIDTH = $clog2(BLOCKS),                             // Number of bits in index
    parameter OFFSET_WIDTH = $clog2(DATA_WIDTH/8),                      // Number of bits in byte offset
    parameter TAG_WIDTH = ADDR_WIDTH - INDEX_WIDTH - OFFSET_WIDTH       // Number of bits in tag
)(
    input wire clk,                                                     // Clock
    input wire reset,                                                   // Reset

    input wire [INDEX_WIDTH-1:0] index,                                 // Input index from CPU request
    output wire [TAG_WIDTH-1:0] tag_out,                                // Tag data output
    output wire [DATA_WIDTH-1:0] data_out,                              // Cache memory data output
    output wire valid_out,                                              // Valid bit output
    output wire dirty_out,                                              // Dirty bit output

    input wire write_en,                                                // Write enable signal
    input wire [TAG_WIDTH-1:0] tag_in,                                  // Tag data input
    input wire [DATA_WIDTH-1:0] data_in,                                // Cache memory data input
    input wire valid_in,                                                // Valid bit input
    input wire dirty_in                                                 // Dirty bit input
);

    // Cache memory register
    reg [TAG_WIDTH-1:0] tag_array [0:BLOCKS-1];
    reg [DATA_WIDTH-1:0] data_array [0:BLOCKS-1];
    reg valid_array [0:BLOCKS-1];
    reg dirty_array [0:BLOCKS-1];

    integer i;

    // Combinational output of given index
    assign tag_out = tag_array[index];
    assign data_out = data_array[index];
    assign valid_out = valid_array[index];
    assign dirty_out = dirty_array[index];

    // Sequential reset and write operation
    always @(posedge clk) begin
        if (reset) begin
            for (i = 0; i < BLOCKS; i = i + 1) begin
                tag_array[i] <= {TAG_WIDTH{1'b0}};
                data_array[i] <= {DATA_WIDTH{1'b0}};
                valid_array[i] <= 1'b0;
                dirty_array[i] <= 1'b0;
            end
        end
        else if (write_en) begin
            tag_array[index] <= tag_in;
            data_array[index] <= data_in;
            valid_array[index] <= valid_in;
            dirty_array[index] <= dirty_in;
        end
    end
endmodule

direct_mapped_cache.v
`timescale 1ns/1ps

module direct_mapped_cache #(
    parameter ADDR_WIDTH   = 32,
    parameter DATA_WIDTH   = 32,
    parameter BLOCKS    = 16,
    parameter INDEX_WIDTH  = $clog2(BLOCKS),
    parameter OFFSET_WIDTH = $clog2(DATA_WIDTH/8),
    parameter TAG_WIDTH    = ADDR_WIDTH - INDEX_WIDTH - OFFSET_WIDTH
)(
    input wire clk,
    input wire reset,

    // CPU interface
    input  wire                  cpu_req,
    input  wire                  cpu_write,
    input  wire [ADDR_WIDTH-1:0] cpu_addr,
    input  wire [DATA_WIDTH-1:0] cpu_wdata,

    output wire [DATA_WIDTH-1:0] cpu_rdata,
    output wire                  cpu_ready,

    // Memory interface
    output wire                  mem_req,
    output wire                  mem_write,
    output wire [ADDR_WIDTH-1:0] mem_addr,
    output wire [DATA_WIDTH-1:0] mem_wdata,

    input wire [DATA_WIDTH-1:0] mem_rdata,
    input wire                  mem_ready
);

    wire [INDEX_WIDTH-1:0] cache_index;

    wire [TAG_WIDTH-1:0]  cache_tag;
    wire [DATA_WIDTH-1:0] cache_data;

    wire cache_valid;
    wire cache_dirty;

    wire cache_write_en;

    wire [TAG_WIDTH-1:0]  cache_tag_in;
    wire [DATA_WIDTH-1:0] cache_data_in;

    wire cache_valid_in;
    wire cache_dirty_in;


    /*
     * Cache storage
     */

    cache_memory #(
        .ADDR_WIDTH   (ADDR_WIDTH),
        .DATA_WIDTH   (DATA_WIDTH),
        .BLOCKS    (BLOCKS),
        .INDEX_WIDTH  (INDEX_WIDTH),
        .OFFSET_WIDTH (OFFSET_WIDTH),
        .TAG_WIDTH    (TAG_WIDTH)
    ) cache_memory_inst (
        .clk   (clk),
        .reset (reset),

        .index (cache_index),

        .tag_out   (cache_tag),
        .data_out  (cache_data),
        .valid_out (cache_valid),
        .dirty_out (cache_dirty),

        .write_en (cache_write_en),

        .tag_in   (cache_tag_in),
        .data_in  (cache_data_in),
        .valid_in (cache_valid_in),
        .dirty_in (cache_dirty_in)
    );


    /*
     * Cache controller
     */

    cache_controller #(
        .ADDR_WIDTH   (ADDR_WIDTH),
        .DATA_WIDTH   (DATA_WIDTH),
        .BLOCKS    (BLOCKS),
        .INDEX_WIDTH  (INDEX_WIDTH),
        .OFFSET_WIDTH (OFFSET_WIDTH),
        .TAG_WIDTH    (TAG_WIDTH)
    ) cache_controller_inst (
        .clk   (clk),
        .reset (reset),

        .cpu_req   (cpu_req),
        .cpu_write (cpu_write),
        .cpu_addr  (cpu_addr),
        .cpu_wdata (cpu_wdata),

        .cpu_rdata (cpu_rdata),
        .cpu_ready (cpu_ready),

        .cache_index (cache_index),

        .cache_tag   (cache_tag),
        .cache_data  (cache_data),
        .cache_valid (cache_valid),
        .cache_dirty (cache_dirty),

        .cache_write_en (cache_write_en),

        .cache_tag_in   (cache_tag_in),
        .cache_data_in  (cache_data_in),
        .cache_valid_in (cache_valid_in),
        .cache_dirty_in (cache_dirty_in),

        .mem_req   (mem_req),
        .mem_write (mem_write),
        .mem_addr  (mem_addr),
        .mem_wdata (mem_wdata),

        .mem_rdata (mem_rdata),
        .mem_ready (mem_ready)
    );

endmodule

tb_direct_mapped_cache.v
`timescale 1ns/1ps
module tb_direct_mapped_cache;

    parameter ADDR_WIDTH = 32;
    parameter DATA_WIDTH = 32;
    parameter BLOCKS = 16;
    parameter MEM_WORDS = 256;

    reg clk;
    reg reset;

    reg cpu_req;
    reg cpu_write;
    reg [ADDR_WIDTH-1:0] cpu_addr;
    reg [DATA_WIDTH-1:0] cpu_wdata;

    wire [DATA_WIDTH-1:0] cpu_rdata;
    wire cpu_ready;

    wire mem_req;
    wire mem_write;
    wire [ADDR_WIDTH-1:0] mem_addr;
    wire [DATA_WIDTH-1:0] mem_wdata;

    wire [DATA_WIDTH-1:0] mem_rdata;
    wire mem_ready;

    integer pass_count;
    integer fail_count;

    initial begin
        clk = 1'b0;
        forever #5 clk = ~clk;
    end

    // Cache  initialise
    direct_mapped_cache #(
        .ADDR_WIDTH(ADDR_WIDTH),
        .DATA_WIDTH(DATA_WIDTH),
        .BLOCKS(BLOCKS)
    )DUT(
        .clk(clk),
        .reset(reset),
        .cpu_req(cpu_req),
        .cpu_write(cpu_write),
        .cpu_addr(cpu_addr),
        .cpu_wdata(cpu_wdata),
        .cpu_rdata(cpu_rdata),
        .cpu_ready(cpu_ready),
        .mem_req(mem_req),
        .mem_write(mem_write),
        .mem_addr(mem_addr),
        .mem_wdata(mem_wdata),
        .mem_rdata(mem_rdata),
        .mem_ready(mem_ready)
    );

    //Memory initialise
    main_memory #(
        .ADDR_WIDTH(ADDR_WIDTH),
        .DATA_WIDTH(DATA_WIDTH),
        .MEM_WORDS(MEM_WORDS),
        .LATENCY(3)
    ) MEMORY (
        .clk(clk),
        .reset(reset),
        .mem_req(mem_req),
        .mem_write(mem_write),
        .mem_addr(mem_addr),
        .mem_wdata(mem_wdata),
        .mem_rdata(mem_rdata),
        .mem_ready(mem_ready)
    );

    // TASKS
    task cpu_read;
        input [ADDR_WIDTH-1:0] address;
        input [DATA_WIDTH-1:0] expected;

        begin
            @(negedge clk);
            cpu_addr = address;
            cpu_wdata = 0;
            cpu_write = 1'b0;
            cpu_req = 1'b1;

            @(negedge clk);
            cpu_req = 1'b0;
            wait(cpu_ready == 1'b1);

            if (cpu_rdata === expected) begin
                $display("[PASS] READ addr=%h data=%h",address,cpu_rdata);
                pass_count = pass_count + 1;
            end
            else begin
                $display("[FAIL] READ addr=%h expected=%h got=%h",address,expected,cpu_rdata);
                fail_count = fail_count + 1;
            end
            @(negedge clk);
        end
    endtask

    task cpu_write_task;
        input [ADDR_WIDTH-1:0] address;
        input [DATA_WIDTH-1:0] data;

        begin
            @(negedge clk);
            cpu_addr = address;
            cpu_wdata = data;
            cpu_write = 1'b1;
            cpu_req = 1'b1;

            @(negedge clk);
            cpu_req = 1'b0;
            wait(cpu_ready == 1'b1);

            $display("[WRITE COMPLETE] addr=%h data=%h",address,data);
            @(negedge clk);
        end
    endtask

    // Test Sequence
    initial begin
        $dumpfile("cache.vcd");
        $dumpvars(0, tb_direct_mapped_cache);

        reset = 1'b1;
        cpu_req = 1'b0;
        cpu_write = 1'b0;
        cpu_addr = 0;
        cpu_wdata = 0;

        pass_count = 0;
        fail_count = 0;

        repeat(4) @(posedge clk);
        @(negedge clk);
        reset = 1'b0;

        $display("\nTEST 1: READ MISS");
        cpu_read(32'h00000000,32'h10000000);

        $display("\nTEST 2: READ HIT");
        cpu_read(32'h00000000,32'h10000000);

        $display("\nTEST 3: WRITE HIT");
        cpu_write_task(32'h00000000,32'hDEADBEEF);

        $display("\nTEST 4: READ DIRTY DATA");
        cpu_read(32'h00000000,32'hDEADBEEF);

        $display("\nTEST 5: DIRTY EVICTION");
        cpu_read(32'h00000040,32'h10000010);

        $display("\nTEST 6: VERIFY WRITE BACK");
        cpu_read(32'h00000000,32'hDEADBEEF);

        $display("\nTEST 7: WRITE MISS");
        cpu_write_task(32'h00000084,32'hCAFEBABE);

        $display("\nTEST 8: VERIFY WRITE ALLOCATE");
        cpu_read(32'h0000_0084,32'hCAFE_BABE);

        $display("CACHE TEST SUMMARY");
        $display("PASS = %0d", pass_count);
        $display("FAIL = %0d", fail_count);

        if (fail_count == 0)
            $display("ALL TESTS PASSED");
        else
            $display("CACHE TEST FAILED");
        #20;
        $finish;
    end

    // Watchdog Timer
    initial begin
        #10000;
        $display("[FATAL] Simulation timeout - possible deadlock");
        $finish;
    end
endmodule

cache.vcd
$date
	Sun Jul 12 00:47:24 2026
$end
$version
	Icarus Verilog
$end
$timescale
	1ps
$end
$scope module tb_direct_mapped_cache $end
$var wire 1 ! mem_write $end
$var wire 32 " mem_wdata [31:0] $end
$var wire 1 # mem_req $end
$var wire 1 $ mem_ready $end
$var wire 32 % mem_rdata [31:0] $end
$var wire 32 & mem_addr [31:0] $end
$var wire 1 ' cpu_ready $end
$var wire 32 ( cpu_rdata [31:0] $end
$var parameter 32 ) ADDR_WIDTH $end
$var parameter 32 * BLOCKS $end
$var parameter 32 + DATA_WIDTH $end
$var parameter 32 , MEM_WORDS $end
$var reg 1 - clk $end
$var reg 32 . cpu_addr [31:0] $end
$var reg 1 / cpu_req $end
$var reg 32 0 cpu_wdata [31:0] $end
$var reg 1 1 cpu_write $end
$var reg 1 2 reset $end
$var integer 32 3 fail_count [31:0] $end
$var integer 32 4 pass_count [31:0] $end
$scope module DUT $end
$var wire 1 - clk $end
$var wire 32 5 cpu_addr [31:0] $end
$var wire 1 / cpu_req $end
$var wire 32 6 cpu_wdata [31:0] $end
$var wire 1 1 cpu_write $end
$var wire 1 2 reset $end
$var wire 1 ! mem_write $end
$var wire 32 7 mem_wdata [31:0] $end
$var wire 1 # mem_req $end
$var wire 1 $ mem_ready $end
$var wire 32 8 mem_rdata [31:0] $end
$var wire 32 9 mem_addr [31:0] $end
$var wire 1 ' cpu_ready $end
$var wire 32 : cpu_rdata [31:0] $end
$var wire 1 ; cache_write_en $end
$var wire 1 < cache_valid_in $end
$var wire 1 = cache_valid $end
$var wire 26 > cache_tag_in [25:0] $end
$var wire 26 ? cache_tag [25:0] $end
$var wire 4 @ cache_index [3:0] $end
$var wire 1 A cache_dirty_in $end
$var wire 1 B cache_dirty $end
$var wire 32 C cache_data_in [31:0] $end
$var wire 32 D cache_data [31:0] $end
$var parameter 32 E ADDR_WIDTH $end
$var parameter 32 F BLOCKS $end
$var parameter 32 G DATA_WIDTH $end
$var parameter 32 H INDEX_WIDTH $end
$var parameter 32 I OFFSET_WIDTH $end
$var parameter 34 J TAG_WIDTH $end
$scope module cache_controller_inst $end
$var wire 1 K cache_hit $end
$var wire 4 L cache_index [3:0] $end
$var wire 1 - clk $end
$var wire 32 M cpu_addr [31:0] $end
$var wire 1 / cpu_req $end
$var wire 32 N cpu_wdata [31:0] $end
$var wire 1 1 cpu_write $end
$var wire 1 2 reset $end
$var wire 26 O req_tag [25:0] $end
$var wire 4 P req_index [3:0] $end
$var wire 1 $ mem_ready $end
$var wire 32 Q mem_rdata [31:0] $end
$var wire 1 = cache_valid $end
$var wire 26 R cache_tag [25:0] $end
$var wire 1 B cache_dirty $end
$var wire 32 S cache_data [31:0] $end
$var parameter 32 T ADDR_WIDTH $end
$var parameter 3 U ALLOCATE $end
$var parameter 32 V BLOCKS $end
$var parameter 32 W DATA_WIDTH $end
$var parameter 3 X IDLE $end
$var parameter 32 Y INDEX_WIDTH $end
$var parameter 3 Z LOOKUP $end
$var parameter 32 [ OFFSET_WIDTH $end
$var parameter 34 \ TAG_WIDTH $end
$var parameter 3 ] UPDATE $end
$var parameter 3 ^ WRITE_BACK $end
$var reg 32 _ cache_data_in [31:0] $end
$var reg 1 A cache_dirty_in $end
$var reg 26 ` cache_tag_in [25:0] $end
$var reg 1 < cache_valid_in $end
$var reg 1 ; cache_write_en $end
$var reg 32 a cpu_rdata [31:0] $end
$var reg 1 ' cpu_ready $end
$var reg 32 b mem_addr [31:0] $end
$var reg 1 # mem_req $end
$var reg 32 c mem_wdata [31:0] $end
$var reg 1 ! mem_write $end
$var reg 32 d req_addr [31:0] $end
$var reg 32 e req_wdata [31:0] $end
$var reg 1 f req_write $end
$var reg 3 g state [2:0] $end
$upscope $end
$scope module cache_memory_inst $end
$var wire 1 - clk $end
$var wire 32 h data_in [31:0] $end
$var wire 32 i data_out [31:0] $end
$var wire 1 A dirty_in $end
$var wire 1 B dirty_out $end
$var wire 4 j index [3:0] $end
$var wire 1 2 reset $end
$var wire 26 k tag_in [25:0] $end
$var wire 26 l tag_out [25:0] $end
$var wire 1 < valid_in $end
$var wire 1 = valid_out $end
$var wire 1 ; write_en $end
$var parameter 32 m ADDR_WIDTH $end
$var parameter 32 n BLOCKS $end
$var parameter 32 o DATA_WIDTH $end
$var parameter 32 p INDEX_WIDTH $end
$var parameter 32 q OFFSET_WIDTH $end
$var parameter 34 r TAG_WIDTH $end
$var integer 32 s i [31:0] $end
$upscope $end
$upscope $end
$scope module MEMORY $end
$var wire 1 - clk $end
$var wire 32 t mem_addr [31:0] $end
$var wire 1 # mem_req $end
$var wire 32 u mem_wdata [31:0] $end
$var wire 1 ! mem_write $end
$var wire 1 2 reset $end
$var wire 8 v saved_word_addr [7:0] $end
$var parameter 32 w ADDR_WIDTH $end
$var parameter 32 x DATA_WIDTH $end
$var parameter 32 y LATENCY $end
$var parameter 32 z MEM_AWIDTH $end
$var parameter 32 { MEM_WORDS $end
$var parameter 32 | OFFSET_WIDTH $end
$var reg 1 } busy $end
$var reg 32 ~ mem_rdata [31:0] $end
$var reg 1 $ mem_ready $end
$var reg 32 !" saved_addr [31:0] $end
$var reg 32 "" saved_wdata [31:0] $end
$var reg 1 #" saved_write $end
$var integer 32 $" counter [31:0] $end
$var integer 32 %" i [31:0] $end
$upscope $end
$scope task cpu_read $end
$var reg 32 &" address [31:0] $end
$var reg 32 '" expected [31:0] $end
$upscope $end
$scope task cpu_write_task $end
$var reg 32 (" address [31:0] $end
$var reg 32 )" data [31:0] $end
$upscope $end
$upscope $end
$enddefinitions $end
$comment Show the parameter values. $end
$dumpall
b10 |
b100000000 {
b1000 z
b11 y
b100000 x
b100000 w
b11010 r
b10 q
b100 p
b100000 o
b10000 n
b100000 m
b10 ^
b100 ]
b11010 \
b10 [
b1 Z
b100 Y
b0 X
b100000 W
b10000 V
b11 U
b100000 T
b11010 J
b10 I
b100 H
b100000 G
b10000 F
b100000 E
b100000000 ,
b100000 +
b10000 *
b100000 )
$end
#0
$dumpvars
bx )"
bx ("
bx '"
bx &"
b100000000 %"
bx $"
x#"
bx ""
bx !"
bx ~
x}
bx v
bx u
bx t
bx s
bx l
bx k
bx j
bx i
bx h
bx g
xf
bx e
bx d
bx c
bx b
bx a
bx `
bx _
bx S
bx R
bx Q
bx P
bx O
b0 N
b0 M
bx L
xK
bx D
bx C
xB
xA
bx @
bx ?
bx >
x=
x<
x;
bx :
bx 9
bx 8
bx 7
b0 6
b0 5
b0 4
b0 3
12
01
b0 0
0/
b0 .
0-
bx (
x'
bx &
bx %
x$
x#
bx "
x!
$end
#5000
0K
b0 O
b0 ?
b0 R
b0 l
b0 D
b0 S
b0 i
0=
0B
b0 @
b0 L
b0 j
b0 P
b0 v
b0 "
b0 7
b0 c
b0 u
b0 &
b0 9
b0 b
b0 t
0!
0#
0A
0<
b0 C
b0 _
b0 h
b0 >
b0 `
b0 k
0;
0'
b0 (
b0 :
b0 a
0f
b0 e
b0 d
b0 g
b0 $"
b0 ""
b0 !"
0#"
b0 %
b0 8
b0 Q
b0 ~
0$
0}
b10000 s
1-
#10000
0-
#15000
b10000 s
1-
#20000
0-
#25000
b10000 s
1-
#30000
0-
#35000
b10000 s
1-
#40000
b10000000000000000000000000000 '"
b0 &"
02
0-
#45000
1-
#50000
1/
0-
#55000
b1 g
1-
#60000
0/
0-
#65000
1#
b11 g
1-
#70000
0-
#75000
b11 $"
1}
1-
#80000
0-
#85000
b10 $"
1-
#90000
0-
#95000
b1 $"
1-
#100000
0-
#105000
0#
b10000000000000000000000000000 %
b10000000000000000000000000000 8
b10000000000000000000000000000 Q
b10000000000000000000000000000 ~
1$
0}
1-
#110000
0-
#115000
b1 4
0$
b0 g
1'
b10000000000000000000000000000 (
b10000000000000000000000000000 :
b10000000000000000000000000000 a
1<
b10000000000000000000000000000 C
b10000000000000000000000000000 _
b10000000000000000000000000000 h
1;
1-
#120000
0-
#125000
1K
1=
b10000000000000000000000000000 D
b10000000000000000000000000000 S
b10000000000000000000000000000 i
0;
0'
1-
#130000
1/
0-
#135000
b1 g
1-
#140000
0/
0-
#145000
b10 4
b0 g
1'
1-
#150000
b11011110101011011011111011101111 )"
b0 ("
0-
#155000
0'
1-
#160000
1/
11
b11011110101011011011111011101111 0
b11011110101011011011111011101111 6
b11011110101011011011111011101111 N
0-
#165000
b1 g
1f
b11011110101011011011111011101111 e
1-
#170000
0/
0-
#175000
b0 g
1'
1A
b11011110101011011011111011101111 C
b11011110101011011011111011101111 _
b11011110101011011011111011101111 h
1;
1-
#180000
b11011110101011011011111011101111 '"
0-
#185000
1B
b11011110101011011011111011101111 D
b11011110101011011011111011101111 S
b11011110101011011011111011101111 i
0;
0'
1-
#190000
1/
01
b0 0
b0 6
b0 N
0-
#195000
b1 g
0f
b0 e
1-
#200000
0/
0-
#205000
b11 4
b0 g
1'
b11011110101011011011111011101111 (
b11011110101011011011111011101111 :
b11011110101011011011111011101111 a
1-
#210000
b10000000000000000000000010000 '"
b1000000 &"
0-
#215000
0'
1-
#220000
1/
b1000000 .
b1000000 5
b1000000 M
0-
#225000
0K
b1 O
b1 g
b1000000 d
1-
#230000
0/
0-
#235000
b11011110101011011011111011101111 "
b11011110101011011011111011101111 7
b11011110101011011011111011101111 c
b11011110101011011011111011101111 u
1!
1#
b10 g
1-
#240000
0-
#245000
b11 $"
b11011110101011011011111011101111 ""
1#"
1}
1-
#250000
0-
#255000
b10 $"
1-
#260000
0-
#265000
b1 $"
1-
#270000
0-
#275000
b0 "
b0 7
b0 c
b0 u
0!
0#
1$
0}
1-
#280000
0-
#285000
b1000000 &
b1000000 9
b1000000 b
b1000000 t
1#
b11 g
0$
1-
#290000
0-
#295000
b10000 v
b11 $"
b0 ""
b1000000 !"
0#"
1}
1-
#300000
0-
#305000
b10 $"
1-
#310000
0-
#315000
b1 $"
1-
#320000
0-
#325000
b0 &
b0 9
b0 b
b0 t
0#
b10000000000000000000000010000 %
b10000000000000000000000010000 8
b10000000000000000000000010000 Q
b10000000000000000000000010000 ~
1$
0}
1-
#330000
0-
#335000
b100 4
0$
b0 g
1'
b10000000000000000000000010000 (
b10000000000000000000000010000 :
b10000000000000000000000010000 a
0A
b10000000000000000000000010000 C
b10000000000000000000000010000 _
b10000000000000000000000010000 h
b1 >
b1 `
b1 k
1;
1-
#340000
b11011110101011011011111011101111 '"
b0 &"
0-
#345000
1K
0B
b10000000000000000000000010000 D
b10000000000000000000000010000 S
b10000000000000000000000010000 i
b1 ?
b1 R
b1 l
0;
0'
1-
#350000
1/
b0 .
b0 5
b0 M
0-
#355000
0K
b0 O
b1 g
b0 d
1-
#360000
0/
0-
#365000
1#
b11 g
1-
#370000
0-
#375000
b0 v
b11 $"
b0 !"
1}
1-
#380000
0-
#385000
b10 $"
1-
#390000
0-
#395000
b1 $"
1-
#400000
0-
#405000
0#
b11011110101011011011111011101111 %
b11011110101011011011111011101111 8
b11011110101011011011111011101111 Q
b11011110101011011011111011101111 ~
1$
0}
1-
#410000
0-
#415000
b101 4
0$
b0 g
1'
b11011110101011011011111011101111 (
b11011110101011011011111011101111 :
b11011110101011011011111011101111 a
b11011110101011011011111011101111 C
b11011110101011011011111011101111 _
b11011110101011011011111011101111 h
b0 >
b0 `
b0 k
1;
1-
#420000
b11001010111111101011101010111110 )"
b10000100 ("
0-
#425000
1K
b11011110101011011011111011101111 D
b11011110101011011011111011101111 S
b11011110101011011011111011101111 i
b0 ?
b0 R
b0 l
0;
0'
1-
#430000
1/
11
b11001010111111101011101010111110 0
b11001010111111101011101010111110 6
b11001010111111101011101010111110 N
b10000100 .
b10000100 5
b10000100 M
0-
#435000
0K
b10 O
b0 D
b0 S
b0 i
0=
b1 @
b1 L
b1 j
b1 P
b1 g
1f
b11001010111111101011101010111110 e
b10000100 d
1-
#440000
0/
0-
#445000
b10000100 &
b10000100 9
b10000100 b
b10000100 t
1#
b11 g
1-
#450000
0-
#455000
b100001 v
b11 $"
b10000100 !"
1}
1-
#460000
0-
#465000
b10 $"
1-
